fairlay/__init__.py
fairlay/api.py
fairlay/utils.py
fairlay-0.1.3.dist-info/LICENSE.md
fairlay-0.1.3.dist-info/WHEEL
fairlay-0.1.3.dist-info/METADATA
fairlay-0.1.3.dist-info/RECORD
