Metadata-Version: 2.1
Name: fairlay
Version: 0.1.3
Summary: Fairlay Client for Python 3.8+
License: MIT
Author: jim zhou
Author-email: 43537315+jimtje@users.noreply.github.com
Requires-Python: >=3.8,<4.0
Classifier: License :: OSI Approved :: MIT License
Classifier: Programming Language :: Python :: 3
Classifier: Programming Language :: Python :: 3.8
Classifier: Programming Language :: Python :: 3.9
Requires-Dist: arrow (>=1.0.3,<2.0.0)
Requires-Dist: httpx (>=0.17.1,<0.18.0)
Requires-Dist: marshmallow (>=3.10.0,<4.0.0)
Requires-Dist: marshmallow-enum (>=1.5.1,<2.0.0)
Requires-Dist: pycryptodome (>=3.10.1,<4.0.0)
Requires-Dist: requests (>=2.25.1,<3.0.0)
Requires-Dist: ujson (>=4.0.2,<5.0.0)
